<?xml version="1.0" encoding="utf-8"?>

<!-- Be sure to use the new v1.1 namespace to utilize the new PhraseTopic feature -->
<VoiceCommands xmlns="http://schemas.microsoft.com/voicecommands/1.1">
  <!-- The CommandSet Name is used to programmatically access the CommandSet -->

  <CommandSet xml:lang="en-us" Name="Repeat">
    <!-- The CommandPrefix provides an alternative to your full app name for invocation -->
    <CommandPrefix>Repeat</CommandPrefix>

    <!-- The CommandSet Example appears in the global help alongside your app name -->
    <Example>she's cool</Example>

    <Command Name="NaturalLanguage">
      <Example> She's cool </Example>
      <ListenFor>[Cortana] {naturalLanguage} </ListenFor>
      <Feedback> Got it... </Feedback>
      <Navigate Target="MainPage.xaml" />
    </Command>

    <PhraseTopic Label="naturalLanguage" Scenario="Natural Language">
      <Subject>Repeat</Subject>
    </PhraseTopic>

  </CommandSet>

</VoiceCommands>